main.py
tempconverter2025_user-0.1.dist-info/METADATA
tempconverter2025_user-0.1.dist-info/WHEEL
tempconverter2025_user-0.1.dist-info/top_level.txt
tempconverter2025_user-0.1.dist-info/RECORD
